nestly/__init__.py
nestly/_py3.py
nestly/core.py
nestly/scons.py
nestly/scripts/__init__.py
nestly/scripts/nestagg.py
nestly/scripts/nestrun.py
nestly/test/__init__.py
nestly/test/test_core.py
nestly/test/test_scons.py
nestly-0.6.1.dist-info/DESCRIPTION.rst
nestly-0.6.1.dist-info/METADATA
nestly-0.6.1.dist-info/RECORD
nestly-0.6.1.dist-info/WHEEL
nestly-0.6.1.dist-info/entry_points.txt
nestly-0.6.1.dist-info/metadata.json
nestly-0.6.1.dist-info/top_level.txt
