Metadata-Version: 2.0
Name: nestly
Version: 0.6.1
Summary: Nestly is a collection of functions designed to make
Home-page: https://github.com/fhcrc/nestly
Author: Erick Matsen
Author-email: matsen@fhcrc.org
License: UNKNOWN
Platform: UNKNOWN
